denseig/__init__.py
denseig/colored_terminal.py
denseig/ig/__init__.py
denseig/ig/integrated_gradients.py
denseig/ig/utils.py
denseig/models/DocModel.py
denseig/models/GenericIGModel.py
denseig/models/QueryModel.py
denseig/models/__init__.py
denseig/utils.py
denseig/wrapers/SentenceTransformerWrapper.py
denseig/wrapers/__init__.py
denseig-0.1.0.dist-info/LICENSE
denseig-0.1.0.dist-info/METADATA
denseig-0.1.0.dist-info/WHEEL
denseig-0.1.0.dist-info/RECORD
