Metadata-Version: 2.1
Name: denseig
Version: 0.1.0
Summary: This package contains the required tools to run dense retriever explainability analysis using integrated gradients.
Author: Goksenin Yuksel
Author-email: Goksenin.yuksel@outlook.com
Requires-Python: >=3.8,<4.0
Classifier: Programming Language :: Python :: 3
Classifier: Programming Language :: Python :: 3.8
Classifier: Programming Language :: Python :: 3.9
Classifier: Programming Language :: Python :: 3.10
Classifier: Programming Language :: Python :: 3.11
Classifier: Programming Language :: Python :: 3.12
Requires-Dist: beir (>=2.0.0,<3.0.0)
Requires-Dist: captum (>=0.6.0,<0.7.0)
Requires-Dist: click (>=8.1.7,<9.0.0)
Requires-Dist: sentence-transformers (>=2.0.0,<3.0.0)
